agentbill_langchain/__init__.py
agentbill_langchain/callback.py
agentbill_langchain/exceptions.py
agentbill_langchain/orders.py
agentbill_langchain/signals.py
agentbill_langchain/tracing.py
agentbill_py_langchain-7.17.3.dist-info/licenses/LICENSE
agentbill_py_langchain-7.17.3.dist-info/METADATA
agentbill_py_langchain-7.17.3.dist-info/WHEEL
agentbill_py_langchain-7.17.3.dist-info/top_level.txt
agentbill_py_langchain-7.17.3.dist-info/RECORD
