Metadata-Version: 2.4
Name: agentbill-py-langchain
Version: 7.17.3
Summary: LangChain callback handler for automatic usage tracking and billing with AgentBill
Home-page: https://github.com/Agent-Bill/langchain
Author: AgentBill
Author-email: AgentBill <dominic@agentbill.io>
License: MIT
Project-URL: Documentation, https://docs.agentbill.io
Project-URL: Repository, https://github.com/Agent-Bill/langchain
Keywords: langchain,agentbill,ai,agent,billing,usage-tracking,openai,anthropic,llm,observability,callbacks
Classifier: Development Status :: 4 - Beta
Classifier: Intended Audience :: Developers
Classifier: Topic :: Software Development :: Libraries :: Python Modules
Classifier: License :: OSI Approved :: MIT License
Classifier: Programming Language :: Python :: 3
Classifier: Programming Language :: Python :: 3.8
Classifier: Programming Language :: Python :: 3.9
Classifier: Programming Language :: Python :: 3.10
Classifier: Programming Language :: Python :: 3.11
Classifier: Programming Language :: Python :: 3.12
Requires-Python: >=3.8
License-File: LICENSE
Requires-Dist: langchain>=0.1.0
Requires-Dist: requests>=2.28.0
Provides-Extra: openai
Requires-Dist: langchain-openai>=0.0.1; extra == "openai"
Provides-Extra: anthropic
Requires-Dist: langchain-anthropic>=0.0.1; extra == "anthropic"
Provides-Extra: dev
Requires-Dist: pytest>=7.0.0; extra == "dev"
Requires-Dist: pytest-cov>=4.0.0; extra == "dev"
Requires-Dist: pylint>=2.15.0; extra == "dev"
Requires-Dist: black>=22.0.0; extra == "dev"
Dynamic: author
Dynamic: home-page
Dynamic: license-file
Dynamic: requires-python
